camar/__init__.py
camar/environment.py
camar/make_env.py
camar/registry.py
camar/utils.py
camar/dynamics/__init__.py
camar/dynamics/base.py
camar/dynamics/diffdrive.py
camar/dynamics/holonomic.py
camar/dynamics/mixed.py
camar/integrations/__init__.py
camar/integrations/torchrl.py
camar/maps/__init__.py
camar/maps/base.py
camar/maps/batched_string_grid.py
camar/maps/caves_cont.py
camar/maps/const.py
camar/maps/labmaze_grid.py
camar/maps/movingai.py
camar/maps/random_grid.py
camar/maps/string_grid.py
camar/maps/utils.py
camar/render/__init__.py
camar/render/const.py
camar/render/matplotlib.py
camar/render/matplotlib_old.py
camar/render/svg.py
camar/render/svg_old.py
camar/render/utils.py
camar/wrappers/__init__.py
camar/wrappers/base.py
camar/wrappers/craftax.py
camar/wrappers/metrics.py
camar-0.4.0.dist-info/METADATA
camar-0.4.0.dist-info/WHEEL
camar-0.4.0.dist-info/licenses/LICENSE
camar-0.4.0.dist-info/RECORD
