Metadata-Version: 2.4
Name: camar
Version: 0.4.0
Summary: CAMAR: A high-performance multi-agent reinforcement learning environment for continuous multi-agent pathfinding
Author-email: Square596 <artem211201@gmail.com>
License-Expression: MIT
License-File: LICENSE
Classifier: Programming Language :: Python :: 3.10
Classifier: Programming Language :: Python :: 3.11
Classifier: Programming Language :: Python :: 3.12
Classifier: Programming Language :: Python :: 3.13
Requires-Python: >=3.10
Requires-Dist: flax>=0.9.0
Requires-Dist: jax>=0.4.31
Provides-Extra: baselines
Requires-Dist: matplotlib>=3.10.1; extra == 'baselines'
Requires-Dist: pandas>=1.4.4; extra == 'baselines'
Requires-Dist: torchrl>=0.7.0; extra == 'baselines'
Requires-Dist: tqdm>=4.67.1; extra == 'baselines'
Requires-Dist: wandb>=0.19.9; extra == 'baselines'
Provides-Extra: benchmarl
Requires-Dist: av<14.0.0; extra == 'benchmarl'
Requires-Dist: hydra-core>=1.3.2; extra == 'benchmarl'
Requires-Dist: id-marl-eval>=0.0.4; extra == 'benchmarl'
Requires-Dist: torchrl>=0.7.0; extra == 'benchmarl'
Requires-Dist: torchvision>=0.21.0; extra == 'benchmarl'
Requires-Dist: tqdm>=4.67.1; extra == 'benchmarl'
Requires-Dist: wandb>=0.19.9; extra == 'benchmarl'
Provides-Extra: cuda12
Requires-Dist: jax[cuda12]>=0.4.31; extra == 'cuda12'
Provides-Extra: labmaze
Requires-Dist: labmaze>=1.0.6; extra == 'labmaze'
Provides-Extra: matplotlib
Requires-Dist: matplotlib>=3.10.1; extra == 'matplotlib'
Provides-Extra: movingai
Requires-Dist: numpy>=1.24.0; extra == 'movingai'
Requires-Dist: opencv-python>=4.5.4.60; extra == 'movingai'
Requires-Dist: requests>=2.20.0; extra == 'movingai'
Provides-Extra: torchrl
Requires-Dist: torchrl>=0.7.0; extra == 'torchrl'
